{
	"url": "http://ko.areumdri.wikidok.net/wp-d/5d1493c28c8118d407ffd731",
	"loadedUrl": "http://ko.areumdri.wikidok.net/wp-d/5d1493c28c8118d407ffd731",
	"wikiTitle": "스칼라 유적",
	"header": [
		"문화·예술",
		"게임",
		"스칼라 유적"
	],
	"postContents": "<div class=\"col-md-12 col-sm-12\">\r\n\t\t\t\t<p>&#xae30;&#xb77c;&#xbc14;&#xb2c8;&#xc544; - &quot;&#xc218;&#xbab0;&#xc720;&#xc801;&quot;<span data-cls=\"foot\" class=\"wiki-fnote\" id=\"#wk_ft1\" contenteditable=\"false\"><button class=\"wiki-fnotepop\" data-container=\".wiki-fnote\" data-placement=\"auto bottom\" data-content=\"%EC%9B%90%EB%AC%B8%EC%9D%80%20%22%EC%88%98%EB%AA%B0%EC%9C%A0%EA%B5%AC(%E6%B0%B4%E6%B2%A1%E9%81%BA%E6%A7%8B)%22%20%EC%8A%A4%EC%B9%BC%EB%9D%BC%20%EC%9C%A0%EC%A0%81.\">1</button></span>&#xa0; &#xc2a4;&#xce7c;&#xb77c;<br>Gyr abania - The Drowned City of Skalla</p><p><br></p><p>&#xc0c1;&#xc704; &#xd56d;&#xbaa9; : <a href=\"/wp-d/590156e6a4e9e1ec1fd5d248/View\" class=\"pjax-link\" data-mce-href=\"/wp-d/590156e6a4e9e1ec1fd5d248/View\">&#xd30c;&#xc774;&#xb110; &#xd310;&#xd0c0;&#xc9c0; 14/&#xc778;&#xc2a4;&#xd134;&#xc2a4; &#xb358;&#xc804;</a></p><p><img src=\"/api/File/Real/5d0e76fc566bcc785c388b76\" width=\"1\" caption=\"false\" data-mce-src=\"/api/File/Real/5d0e76fc566bcc785c388b76\"></p><table class=\"mce-item-table\" style=\"width: 100%;\" data-mce-style=\"width: 100%;\"><tbody><tr style=\"height: 31px;\" data-mce-style=\"height: 31px;\"><td colspan=\"4\" style=\"background-color: #ffc8d2; width: 100%; height: 31px; text-align: center;\" data-mce-style=\"background-color: #ffc8d2; width: 100%; height: 31px; text-align: center;\"><strong>&quot;&#xd64d;&#xb828;&#xc758; &#xd574;&#xbc29;&#xc790;&quot; 4&#xc778; &#xc778;&#xc2a4;&#xd134;&#xc2a4; &#xb358;&#xc804;</strong></td></tr><tr style=\"height: 31px;\" data-mce-style=\"height: 31px;\"><td style=\"width: 20%; background-color: #fffae0; height: 31px; text-align: center;\" data-mce-style=\"width: 20%; background-color: #fffae0; height: 31px; text-align: center;\"><img src=\"http://ko.areumdri.wikidok.net/api/File/Real/5d0faba7e7c3da9d0766e4e3\" data-mce-src=\"/api/File/Real/5d0faba7e7c3da9d0766e4e3\" width=\"120\" caption=\"false\"></td><td style=\"width: 30%; background-color: #fffae0; height: 31px; text-align: center;\" data-mce-style=\"width: 30%; background-color: #fffae0; height: 31px; text-align: center;\"><strong><a href=\"http://ko.areumdri.wikidok.net/wp-d/5d111d6c766286c767bf01b1/View\" class=\"pjax-link\" title=\"&quot;&#xd45c;&#xb958;&#xd574;&#xc5ed;&quot; &#xc138;&#xc774;&#xb80c; &#xd574;\" data-mce-href=\"/wp-d/5d111d6c766286c767bf01b1/View\">&#xc138;&#xc774;&#xb80c; &#xd574;(Lv. 61)</a></strong></td><td style=\"width: 20%; height: 31px; text-align: center;\" data-mce-style=\"width: 20%; height: 31px; text-align: center;\"><img src=\"http://ko.areumdri.wikidok.net/api/File/Real/5d0fac21e7c3da9d0766e4ef\" width=\"120\" caption=\"false\" data-mce-src=\"/api/File/Real/5d0fac21e7c3da9d0766e4ef\"></td><td style=\"width: 30%; height: 31px; text-align: center;\" data-mce-style=\"width: 30%; height: 31px; text-align: center;\"><a href=\"http://ko.areumdri.wikidok.net/wp-d/5d1139bb766286c767bf0695/View\" class=\"pjax-link\" title=\"&quot;&#xd574;&#xc800;&#xad81;&#xc804;&quot; &#xc2dc;&#xc2a4;&#xc774; &#xad81;\" data-mce-href=\"/wp-d/5d1139bb766286c767bf0695/View\">&#xc2dc;&#xc2a4;&#xc774; &#xad81;(Lv. 63)</a></td></tr><tr style=\"height: 31px;\" data-mce-style=\"height: 31px;\"><td style=\"width: 20%; background-color: #fffae0; height: 31px; text-align: center;\" data-mce-style=\"width: 20%; background-color: #fffae0; height: 31px; text-align: center;\"><img src=\"http://ko.areumdri.wikidok.net/api/File/Real/5d0e7694566bcc785c388b51\" width=\"120\" caption=\"false\" data-mce-src=\"/api/File/Real/5d0e7694566bcc785c388b51\"></td><td style=\"width: 30%; background-color: #fffae0; height: 31px; text-align: center;\" data-mce-style=\"width: 30%; background-color: #fffae0; height: 31px; text-align: center;\"><strong><a href=\"http://ko.areumdri.wikidok.net/wp-d/5d115e3e766286c767bf0f5b/View\" class=\"pjax-link\" title=\"&quot;&#xc804;&#xd1b5;&#xc2dc;&#xb828;&quot; &#xbc14;&#xb974;&#xb2f4; &#xd328;&#xb3c4;\" data-mce-href=\"/wp-d/5d115e3e766286c767bf0f5b/View\">&#xbc14;&#xb974;&#xb2f4; &#xd328;&#xb3c4;(Lv. 65)</a></strong></td><td style=\"width: 20%; height: 31px; background-color: #fffae0; text-align: center;\" data-mce-style=\"width: 20%; height: 31px; background-color: #fffae0; text-align: center;\"><img src=\"http://ko.areumdri.wikidok.net/api/File/Real/5d0e76a4566bcc785c388b56\" width=\"120\" caption=\"false\" data-mce-src=\"/api/File/Real/5d0e76a4566bcc785c388b56\"></td><td style=\"width: 20%; height: 31px; background-color: #fffae0; text-align: center;\" data-mce-style=\"width: 20%; height: 31px; background-color: #fffae0; text-align: center;\"><strong><a href=\"http://ko.areumdri.wikidok.net/wp-d/5d119ee47c1caf3a691607e1/View\" class=\"pjax-link\" title=\"&quot;&#xd574;&#xbc29;&#xacb0;&#xc804;&quot; &#xb3c4;&#xb9c8; &#xc131;\" data-mce-href=\"/wp-d/5d119ee47c1caf3a691607e1/View\">&#xb3c4;&#xb9c8; &#xc131;(Lv. 67)</a></strong></td></tr><tr style=\"height: 31px;\" data-mce-style=\"height: 31px;\"><td style=\"width: 20%; background-color: #fffae0; height: 31px; text-align: center;\" data-mce-style=\"width: 20%; background-color: #fffae0; height: 31px; text-align: center;\"><img src=\"http://ko.areumdri.wikidok.net/api/File/Real/5d0e76d2566bcc785c388b6a\" width=\"120\" caption=\"false\" data-mce-src=\"/api/File/Real/5d0e76d2566bcc785c388b6a\"></td><td style=\"width: 30%; background-color: #fffae0; height: 31px; text-align: center;\" data-mce-style=\"width: 30%; background-color: #fffae0; height: 31px; text-align: center;\"><a data-mce-href=\"/wp-d/5d129cf120142900574d8182/View\" href=\"/wp-d/5d129cf120142900574d8182/View\" class=\"pjax-link\" title=\"&quot;&#xac70;&#xb300;&#xd3ec;&#xaca9;&#xc694;&#xc0c8;&quot; &#xce74;&#xc2a4;&#xd2b8;&#xb8f8; &#xc544;&#xbc14;&#xb2c8;&#xc544;\"><strong>&#xce74;&#xc2a4;&#xd2b8;&#xb8f8; &#xc544;&#xbc14;&#xb2c8;&#xc544;(Lv. 69)</strong></a></td><td style=\"width: 20%; height: 31px; background-color: #fffae0; text-align: center;\" data-mce-style=\"width: 20%; height: 31px; background-color: #fffae0; text-align: center;\"><img src=\"http://ko.areumdri.wikidok.net/api/File/Real/5d0e76c5566bcc785c388b66\" width=\"120\" caption=\"false\" data-mce-src=\"/api/File/Real/5d0e76c5566bcc785c388b66\"></td><td style=\"width: 20%; height: 31px; background-color: #fffae0; text-align: center;\" data-mce-style=\"width: 20%; height: 31px; background-color: #fffae0; text-align: center;\"><strong><a href=\"http://ko.areumdri.wikidok.net/wp-d/5d137b7490db932a22947fcc/View\" class=\"pjax-link\" title=\"&quot;&#xd64d;&#xb828;&#xacb0;&#xc804;&quot; &#xc54c;&#xb77c;&#xbbf8;&#xace0;\" data-mce-href=\"/wp-d/5d137b7490db932a22947fcc/View\">&#xc54c;&#xb77c;&#xbbf8;&#xace0;(ILv. 280)</a></strong></td></tr><tr style=\"height: 31px;\" data-mce-style=\"height: 31px;\"><td style=\"width: 20%; height: 31px; text-align: center;\" data-mce-style=\"width: 20%; height: 31px; text-align: center;\"><img src=\"http://ko.areumdri.wikidok.net/api/File/Real/5d0e76de566bcc785c388b6e\" width=\"120\" caption=\"false\" data-mce-src=\"/api/File/Real/5d0e76de566bcc785c388b6e\"></td><td style=\"width: 30%; height: 31px; text-align: center;\" data-mce-style=\"width: 30%; height: 31px; text-align: center;\"><a href=\"/wp-d/5d13e302bb1b6c406eda2d7e/View\" class=\"pjax-link\" title=\"&quot;&#xc545;&#xc778;&#xcc98;&#xb2e8;&quot; &#xcfe0;&#xac00;&#xb124; &#xc131;\" data-mce-href=\"/wp-d/5d13e302bb1b6c406eda2d7e/View\">&#xcfe0;&#xac00;&#xb124; &#xc131;(ILv. 280)</a></td><td style=\"width: 20%; height: 31px; text-align: center;\" data-mce-style=\"width: 20%; height: 31px; text-align: center;\"><img src=\"http://ko.areumdri.wikidok.net/api/File/Real/5d0e76ed566bcc785c388b73\" width=\"120\" caption=\"false\" data-mce-src=\"/api/File/Real/5d0e76ed566bcc785c388b73\"></td><td style=\"width: 30%; height: 31px; text-align: center;\" data-mce-style=\"width: 30%; height: 31px; text-align: center;\"><a data-mce-href=\"/wp-d/5d148b6f8c8118d407ffd58a/View\" href=\"/wp-d/5d148b6f8c8118d407ffd58a/View\" class=\"pjax-link\" title=\"&quot;&#xad34;&#xc2e0;&#xc218;&#xd589;&quot; &#xc131;&#xb3c4;&#xc0b0; &#xc0ac;&#xc6d0;\">&#xc131;&#xb3c4;&#xc0b0; &#xc0ac;&#xc6d0;(ILv. 280)</a></td></tr><tr style=\"height: 31px;\" data-mce-style=\"height: 31px;\"><td style=\"width: 20%; background-color: #fffae0; height: 31px; text-align: center;\" data-mce-style=\"width: 20%; background-color: #fffae0; height: 31px; text-align: center;\"><a data-mce-href=\"/wp-d/5d148b6f8c8118d407ffd58a/View\" href=\"/wp-d/5d148b6f8c8118d407ffd58a/View\" class=\"pjax-link\" title=\"&quot;&#xad34;&#xc2e0;&#xc218;&#xd589;&quot; &#xc131;&#xb3c4;&#xc0b0; &#xc0ac;&#xc6d0;\"><img src=\"http://ko.areumdri.wikidok.net/api/File/Real/5d0e76fc566bcc785c388b76\" width=\"120\" caption=\"false\" data-mce-src=\"/api/File/Real/5d0e76fc566bcc785c388b76\"></a></td><td style=\"width: 30%; background-color: #fffae0; height: 31px; text-align: center;\" data-mce-style=\"width: 30%; background-color: #fffae0; height: 31px; text-align: center;\"><a data-mce-href=\"/wp-d/5d1493c28c8118d407ffd731/View\" href=\"/wp-d/5d1493c28c8118d407ffd731/View\" class=\"pjax-link\" title=\"&quot;&#xc218;&#xbab0;&#xc720;&#xc801;&quot; &#xc2a4;&#xce7c;&#xb77c;\"><strong>&#xc2a4;&#xce7c;&#xb77c; &#xc720;&#xc801;(ILv. 300)</strong></a></td><td style=\"width: 20%; height: 31px; text-align: center;\" data-mce-style=\"width: 20%; height: 31px; text-align: center;\"><a data-mce-href=\"/wp-d/5d148b6f8c8118d407ffd58a/View\" href=\"/wp-d/5d148b6f8c8118d407ffd58a/View\" class=\"pjax-link\" title=\"&quot;&#xad34;&#xc2e0;&#xc218;&#xd589;&quot; &#xc131;&#xb3c4;&#xc0b0; &#xc0ac;&#xc6d0;\"><img src=\"http://ko.areumdri.wikidok.net/api/File/Real/5d0e7708566bcc785c388b7a\" width=\"120\" caption=\"false\" data-mce-src=\"/api/File/Real/5d0e7708566bcc785c388b7a\"></a></td><td style=\"width: 30%; height: 31px; text-align: center;\" data-mce-style=\"width: 30%; height: 31px; text-align: center;\"><a href=\"/wp-d/5d15a8f7b98ac02013a9b5bc/View\" class=\"pjax-link\" title=\"&quot;&#xd64d;&#xc625;&#xd654;&#xc0b0;&quot; &#xc9c0;&#xc625;&#xb69c;&#xaed1;\" data-mce-href=\"/wp-d/5d15a8f7b98ac02013a9b5bc/View\">&#xc9c0;&#xc625;&#xb69c;&#xaed1;(ILv. 310)</a></td></tr><tr style=\"height: 31px;\" data-mce-style=\"height: 31px;\"><td style=\"width: 20%; height: 31px; text-align: center;\" data-mce-style=\"width: 20%; height: 31px; text-align: center;\"><img src=\"http://ko.areumdri.wikidok.net/api/File/Real/5d0e7716566bcc785c388b7f\" width=\"120\" caption=\"false\" data-mce-src=\"/api/File/Real/5d0e7716566bcc785c388b7f\"></td><td style=\"width: 30%; height: 31px; text-align: center;\" data-mce-style=\"width: 30%; height: 31px; text-align: center;\"><a href=\"/wp-d/5d1d03b188a693384ad64c86/View\" class=\"pjax-link\" title=\"&quot;&#xd3ed;&#xc8fc;&#xc804;&#xd568;&quot; &#xbb34;&#xd55c;&#xc5f0;&#xc18d; &#xbc15;&#xbb3c;&#xd568;(&#xc5b4;&#xb824;&#xc6c0;)\" data-mce-href=\"/wp-d/5d1d03b188a693384ad64c86/View\">&#xbb34;&#xd55c;&#xc5f0;&#xc18d; &#xbc15;&#xbb3c;&#xd568;(&#xc5b4;&#xb824;&#xc6c0;)(ILv. 310)</a></td><td style=\"width: 20%; height: 31px; text-align: center;\" data-mce-style=\"width: 20%; height: 31px; text-align: center;\"><img src=\"http://ko.areumdri.wikidok.net/api/File/Real/5d0e7721566bcc785c388b84\" width=\"120\" caption=\"false\" data-mce-src=\"/api/File/Real/5d0e7721566bcc785c388b84\"></td><td style=\"width: 30%; height: 31px; text-align: center;\" data-mce-style=\"width: 30%; height: 31px; text-align: center;\"><a href=\"/wp-d/5d1d0e3188a693384ad64e2f/View\" class=\"pjax-link\" title=\"&quot;&#xd48d;&#xc218;&#xc601;&#xc804;&quot; &#xac15;&#xc5d4; &#xc885;&#xbb18;\" data-mce-href=\"/wp-d/5d1d0e3188a693384ad64e2f/View\">&#xac15;&#xc5d4; &#xc885;&#xbb18;(ILv. 330)</a></td></tr><tr style=\"height: 31px;\" data-mce-style=\"height: 31px;\"><td style=\"width: 20%; background-color: #fffae0; height: 31px; text-align: center;\" data-mce-style=\"width: 20%; background-color: #fffae0; height: 31px; text-align: center;\"><img src=\"http://ko.areumdri.wikidok.net/api/File/Real/5d0e772b566bcc785c388b87\" width=\"120\" caption=\"false\" data-mce-src=\"/api/File/Real/5d0e772b566bcc785c388b87\"></td><td style=\"width: 30%; background-color: #fffae0; height: 31px; text-align: center;\" data-mce-style=\"width: 30%; background-color: #fffae0; height: 31px; text-align: center;\"><strong><a href=\"/wp-d/5d21603f40cbac351edf3e46/View\" class=\"pjax-link\" title=\"&#xc601;&#xad6c; &#xcd08;&#xd1a0;&#xc9c0;&#xb300;\" data-mce-href=\"/wp-d/5d21603f40cbac351edf3e46/View\">&#xc601;&#xad6c; &#xcd08;&#xd1a0;&#xc9c0;&#xb300;(ILv. 340)</a></strong></td><td style=\"width: 20%; height: 31px; text-align: center;\" data-mce-style=\"width: 20%; height: 31px; text-align: center;\"><img src=\"http://ko.areumdri.wikidok.net/api/File/Real/5d0e7737566bcc785c388b8c\" width=\"120\" caption=\"false\" data-mce-src=\"/api/File/Real/5d0e7737566bcc785c388b8c\"></td><td style=\"width: 30%; height: 31px; text-align: center;\" data-mce-style=\"width: 30%; height: 31px; text-align: center;\"><a href=\"/wp-d/5d21701e40cbac351edf441d/View\" class=\"pjax-link\" title=\"&quot;&#xc624;&#xc5fc;&#xb41c; &#xcd08;&#xbaa9;&quot; &#xc131; &#xbaa8;&#xc0e8; &#xc2dd;&#xbb3c;&#xc6d0;(&#xc5b4;&#xb824;&#xc6c0;)\" data-mce-href=\"/wp-d/5d21701e40cbac351edf441d/View\">&#xc131; &#xbaa8;&#xc0e8; &#xc2dd;&#xbb3c;&#xc6d0;(&#xc5b4;&#xb824;&#xc6c0;)(ILv. 340)</a></td></tr><tr style=\"height: 31px;\" data-mce-style=\"height: 31px;\"><td style=\"width: 20%; background-color: #fffae0; height: 31px; text-align: center;\" data-mce-style=\"width: 20%; background-color: #fffae0; height: 31px; text-align: center;\"><img src=\"http://ko.areumdri.wikidok.net/api/File/Real/5d0e7744566bcc785c388b91\" width=\"120\" caption=\"false\" data-mce-src=\"/api/File/Real/5d0e7744566bcc785c388b91\"></td><td style=\"width: 30%; background-color: #fffae0; height: 31px; text-align: center;\" data-mce-style=\"width: 30%; background-color: #fffae0; height: 31px; text-align: center;\"><strong><a href=\"http://ko.areumdri.wikidok.net/wp-d/5d0e777b566bcc785c388ba2/View\" class=\"pjax-link\" title=\"&quot;&#xacbd;&#xacc4;&#xc804;&#xc120;&quot; &#xae40;&#xb9ac;&#xd2b8; &#xd669;&#xc57c;\" data-mce-href=\"/wp-d/5d0e777b566bcc785c388ba2/View\">&#xae40;&#xb9ac;&#xd2b8; &#xd669;&#xc57c;(ILv. 360)</a></strong></td><td style=\"width: 20%; height: 31px; text-align: center;\" data-mce-style=\"width: 20%; height: 31px; text-align: center;\">-</td><td style=\"width: 30%; height: 31px; text-align: center;\" data-mce-style=\"width: 30%; height: 31px; text-align: center;\">-</td></tr></tbody></table><p><br></p><p><br></p><p>&#xc2a4;&#xd018;&#xc5b4; &#xc5d0;&#xb2c9;&#xc2a4; &#xc81c;&#xc791; MMORPG&#xac8c;&#xc784;, &#xd30c;&#xc774;&#xb110; &#xd310;&#xd0c0;&#xc9c0; 14&#xc5d0; &#xb4f1;&#xc7a5;&#xd558;&#xb294; 4&#xc778; &#xc778;&#xc2a4;&#xd134;&#xc2a4; &#xb358;&#xc804; &quot;&#xc2a4;&#xce7c;&#xb77c; &#xc720;&#xc801;&quot;&#xc5d0; &#xb300;&#xd55c; &#xc18c;&#xac1c;&#xae00;.</p><p><br></p><p>&#x203b;&#xc774;&#xd558; &#xb0b4;&#xc6a9;&#xc740; &#xd30c;&#xc774;&#xb110; &#xd310;&#xd0c0;&#xc9c0; 14: &#xd64d;&#xb828;&#xc758; &#xd574;&#xbc29;&#xc790; &#xba54;&#xc778;&#xc2a4;&#xd1a0;&#xb9ac;&#xc758; &#xd575;&#xc2ec;&#xc744; &#xb2f4;&#xace0; &#xc788;&#xae30; &#xb54c;&#xbb38;&#xc5d0; &#xc9c1;&#xc811; &#xd50c;&#xb808;&#xc774; &#xd558;&#xc2e4; &#xbd84;&#xb4e4;&#xc740; &#xc5f4;&#xb78c;&#xc5d0; &#xc8fc;&#xc758;&#xb97c; &#xbd80;&#xd0c1;&#xb4dc;&#xb9bd;&#xb2c8;&#xb2e4;.</p><p><br></p><div contenteditable=\"false\"><div class=\"alert alert-warning\" contenteditable=\"true\" style=\"text-align: center;\" data-mce-style=\"text-align: center;\">&#x203b;&#xc791;&#xc911; &#xc2a4;&#xd3ec;&#xc77c;&#xb7ec; &#xc8fc;&#xc758; : &#xc774; &#xd2c0; &#xc544;&#xb798;&#xb85c;&#xb294; &#xd574;&#xb2f9; &#xc791;&#xd488;&#xc758; &#xd575;&#xc2ec;&#xc801;&#xc778; &#xb0b4;&#xc6a9;&#xc774; &#xc788;&#xc2b5;&#xb2c8;&#xb2e4;.</div></div><p><br></p><p><br></p><h2>1. &#xac1c;&#xc694;</h2><p style=\"text-align: center;\" data-mce-style=\"text-align: center;\"><img src=\"/api/File/Real/5d0e76fc566bcc785c388b76\" caption=\"false\" data-mce-src=\"/api/File/Real/5d0e76fc566bcc785c388b76\" width=\"376\" height=\"120\"></p><blockquote><p style=\"text-align: left;\" data-mce-style=\"text-align: left;\">&#xba3c; &#xc61b;&#xb0a0;, &#xc81c;5 &#xc131;&#xb825; &#xcd08;&#xae30;. &#xae30;&#xb77c;&#xbc14;&#xb2c8;&#xc544; &#xb545;&#xc5d0; &apos;&#xc2a4;&#xce7c;&#xb77c;&apos; &#xb77c;&#xb294; &#xc791;&#xc740; &#xb098;&#xb77c;&#xac00; &#xc788;&#xc5c8;&#xb2e4;. &#xadf8;&#xb4e4;&#xc740; &#xc218;&#xbc31; &#xb144;&#xc5d0; &#xac78;&#xccd0; &#xd5d8;&#xc900;&#xd55c; &#xd611;&#xace1;&#xc5d0; &#xd6cc;&#xb96d;&#xd55c; &#xc11d;&#xc870; &#xb3c4;&#xc2dc;&#xb97c; &#xc138;&#xc6cc;&#xc62c;&#xb838;&#xc73c;&#xb098;, &#xc804;&#xb780;&#xc758; &#xc2dc;&#xb300;&#xb97c; &#xbc84;&#xd168;&#xb0b4;&#xc9c0; &#xbabb;&#xd558;&#xace0; &#xba78;&#xb9dd;&#xd558;&#xace0; &#xb9d0;&#xc558;&#xb2e4;. &#xadf8;&#xb9ac;&#xace0; &#xadf8; &#xc720;&#xc801;&#xc740; &#xc81c;6 &#xc7ac;&#xd574;&#xc758; &#xb300;&#xd64d;&#xc218;&#xc5d0; &#xc758;&#xd574; &apos;&#xb85c;&#xd750; &#xc140; &#xd638;&#xc218;&apos; &#xbc11;&#xbc14;&#xb2e5;&#xc73c;&#xb85c; &#xac00;&#xb77c;&#xc549;&#xc558;&#xb2e4;&#xace0; &#xd55c;&#xb2e4;. &#xadf8;&#xb9ac;&#xace0; &#xc9c0;&#xae08;, &#xc54c;&#xb77c;&#xbbf8;&#xace0;&#xb97c; &#xd574;&#xbc29;&#xc2dc;&#xd0a8; &#xbe5b;&#xc758; &#xc804;&#xc0ac;&#xb4e4;&#xc740; &#xc0c8;&#xb85c;&#xc6b4; &#xbaa8;&#xd5d8;&#xacfc; &#xc228;&#xaca8;&#xc9c4; &#xbcf4;&#xbb3c;&#xc744; &#xcc3e;&#xc544;, &#xc5fc;&#xd638; &#xbc11;&#xbc14;&#xb2e5;&#xc5d0; &#xc7a0;&#xb4e4;&#xc5b4; &#xc788;&#xb294; &#xbe44;&#xc6b4;&#xc758; &#xc11d;&#xc870; &#xb3c4;&#xc2dc;&#xb85c; &#xd5a5;&#xd55c;&#xb2e4;.</p><p style=\"text-align: right;\" data-mce-style=\"text-align: right;\"><strong>- &#xd30c;&#xc774;&#xb110; &#xd310;&#xd0c0;&#xc9c0; 14 &#xc778;&#xc2a4;&#xd134;&#xc2a4; &#xb358;&#xc804; &quot;&#xc2a4;&#xce7c;&#xb77c; &#xc720;&#xc801;&quot; &#xc18c;&#xac1c;&#xbb38;</strong></p></blockquote><p>4.1 &#xd328;&#xce58;&#xb85c; &#xd574;&#xae08;&#xb41c; &#xb358;&#xc804;&#xc774;&#xc790;, 4.1 &#xba54;&#xc778; &#xd018;&#xc2a4;&#xd2b8; &quot;&#xc601;&#xc6c5;&#xc758; &#xadc0;&#xd658;&quot;&#xc744; &#xc9c4;&#xd589;&#xd558;&#xba74; &#xd574;&#xae08;&#xb418;&#xb294; 4&#xc778; &#xc778;&#xc2a4;&#xd134;&#xc2a4; &#xb358;&#xc804;&#xc73c;&#xb85c; 70&#xb808;&#xbca8;&#xc5d0; &#xc785;&#xc7a5;&#xc774; &#xac00;&#xb2a5;&#xd558;&#xb2e4;. &#xc54c;&#xb77c;&#xbbf8;&#xace0; &#xd574;&#xbc29; &#xc774;&#xd6c4; &#xd574;&#xbc29;&#xad70;&#xc740; &#xc54c;&#xb77c;&#xbbf8;&#xace0; &#xd1b5;&#xce58;&#xc5d0; &#xb300;&#xd574; &#xace0;&#xbbfc;&#xd558;&#xace0; &#xc788;&#xb358; &#xcc28;&#xc5d0; &#xc0c8;&#xbcbd;&#xc758; &#xd608;&#xb9f9; &#xc77c;&#xc6d0;&#xc778; &#xbaa8;&#xd5d8;&#xac00; &#xc544;&#xb80c;&#xbc1c;&#xb4dc;&#xb294; &#xbe5b;&#xc758; &#xc804;&#xc0ac;&#xc5d0;&#xac8c; &#xc54c;&#xd53c;&#xb178;&#xc640; &#xd568;&#xaed8; &#xc0c8;&#xb85c;&#xc6b4; &#xbaa8;&#xd5d8;&#xc744; &#xd574;&#xbcf4;&#xc9c0; &#xc54a;&#xaca0;&#xb0d0;&#xba70; &#xc81c;&#xc548;&#xc744; &#xd55c;&#xb2e4;. &#xc544;&#xb80c;&#xbc1c;&#xb4dc;&#xac00; &#xb9d0;&#xd55c; &#xc0c8;&#xb85c;&#xc6b4; &#xbaa8;&#xd5d8;&#xc774;&#xb780; &#xc989;&#xc2a8; &#xc0ac;&#xb77c;&#xc9c4; &apos;&#xd3d0;&#xc655;&#xc758; &#xd669;&#xae08;&apos;&#xc744; &#xcc3e;&#xc73c;&#xb7ec; &#xac00;&#xc790;&#xb294; &#xac83;. &#xd574;&#xbc29; &#xc774;&#xd6c4; &#xc54c;&#xb77c;&#xbbf8;&#xace0; &#xc655;&#xad81;&#xc744; &#xba3c;&#xc800; &#xc0c5;&#xc0c5;&#xc774; &#xcc3e;&#xc740; &#xc774;&#xb4e4;&#xc774; &#xc788;&#xc5c8;&#xc73c;&#xb098; &apos;&#xd3d0;&#xc655;&#xc758; &#xd669;&#xae08;&apos;&#xc740; &#xc544;&#xbb34;&#xb370;&#xb3c4; &#xc548; &#xb098;&#xc640;&#xc11c; &#xadf8; &#xc18c;&#xbb38; &#xb9c8;&#xc800; &#xc0ac;&#xadf8;&#xb77c;&#xb4e0; &#xc0c1;&#xd669;&#xc774;&#xc5c8;&#xb2e4;. &#xac70;&#xae30;&#xc5d0; &#xbfb0;&#xc871;&#xd55c; &#xc815;&#xbcf4;&#xb3c4; &#xc5c6;&#xb358; &#xd130;&#xb77c; &#xc54c;&#xd53c;&#xb178;&#xb294; &#xc5d0;&#xc624;&#xb974;&#xc81c;&#xc544; &#xb3d9;&#xb9f9;&#xad70;&#xc5d0;&#xc11c; &#xc555;&#xc218;&#xd55c; &#xc81c;&#xad6d;&#xad70;&#xc758; &#xae30;&#xb85d;&#xc744;, &#xc544;&#xb80c;&#xbc1c;&#xb4dc;&#xc640; &#xbe5b;&#xc758; &#xc804;&#xc0ac;&#xb294; &#xac01;&#xc790; &#xbcc0;&#xbc29;&#xc9c0;&#xb300;&#xc640; &#xc0b0;&#xc545;&#xc9c0;&#xb300;, &#xc54c;&#xb77c;&#xbbf8;&#xace0;&#xc778; &#xac70;&#xc8fc;&#xad6c;&#xc5d0;&#xc11c; &#xc815;&#xbcf4;&#xb97c; &#xbaa8;&#xc73c;&#xae30;&#xb85c; &#xd55c;&#xb2e4;.</p><p><br></p><p>&#xc54c;&#xb77c;&#xbbf8;&#xace0;&#xc778; &#xac70;&#xc8fc;&#xad6c;&#xc5d0;&#xc11c; &#xd0d0;&#xbb38; &#xc870;&#xc0ac;&#xb97c; &#xc2dc;&#xc791;&#xd55c; &#xbe5b;&#xc758; &#xc804;&#xc0ac;. &#xc655;&#xc815; &#xc2dc;&#xb300;&#xc5d0; &#xc655;&#xad81;&#xc744; &#xb4dc;&#xb098;&#xb4e4;&#xc5c8;&#xb358; &#xc804;&#xc9c1; &#xc11c;&#xae30;&#xad00; &apos;&#xc5d0;&#xb974;&#xb180;&#xb4dc;&apos;&#xb97c; &#xcc3e;&#xc544;&#xac00;&#xc11c; &#xadf8; &#xb2f9;&#xc2dc;&#xc758; &#xc0c1;&#xd669;&#xc5d0; &#xb300;&#xd574; &#xb4e3;&#xac8c; &#xb41c;&#xb2e4;. &#xc655;&#xc704;&#xb97c; &#xbe7c;&#xc557;&#xae34;&#xb2e4;&#xace0; &#xcc29;&#xac01;&#xd55c; &#xd14c;&#xc624;&#xb3c4;&#xb9ac;&#xd06c; &#xc655;&#xc740; &#xc655;&#xc871;&#xc744; &#xc787;&#xb530;&#xb77c; &#xacf5;&#xac1c; &#xcc98;&#xd615;&#xd588;&#xb358; &#xc0ac;&#xc2e4;&#xc774; &#xc788;&#xc5c8;&#xb294;&#xb370;, &#xadf8;&#xbcf4;&#xb2e4; &#xd6e8;&#xc52c; &#xb054;&#xcc0d;&#xd55c; &#xcc98;&#xd615; &#xbc29;&#xbc95;&#xc744; &#xc0dd;&#xac01;&#xd574; &#xb0c8;&#xb2e4;&#xace0; &#xd55c;&#xb2e4;. &#xadf8; &#xb054;&#xcc0d;&#xd55c; &#xcc98;&#xd615;&#xbc29;&#xbc95;&#xc740; &#xbc14;&#xb85c; &#xc790;&#xc2e0;&#xc758; &#xc655;&#xc704;&#xb97c; &#xbe7c;&#xc557;&#xb294;&#xb2e4;&#xb294; &#xb204;&#xba85;&#xc744; &#xc4f0;&#xace0; &#xc7a1;&#xd600;&#xc628; &#xc655;&#xc871;&#xb4e4;&#xc5d0;&#xac8c; &#xad81;&#xc911; &#xc8fc;&#xc220;&#xc0ac;&#xb97c; &#xc2dc;&#xcf1c; &#xc800;&#xc8fc;&#xb97c; &#xac78;&#xc5b4; &#xad34;&#xbb3c; &#xac19;&#xc740; &#xbaa8;&#xc2b5;&#xc73c;&#xb85c; &#xbcc0;&#xc774;&#xc2dc;&#xd0a8; &#xb4a4;, &#xbcc0;&#xc774;&#xd55c; &#xc790;&#xb4e4;&#xc744; &#xc9c0;&#xd558;&#xb85c; &#xb5a8;&#xc5b4;&#xd2b8;&#xb838;&#xb2e4;&#xb294; &#xac83;. &#xb2e4;&#xc2dc; &#xc54c;&#xd53c;&#xb178;&#xc640; &#xc544;&#xb80c;&#xbc1c;&#xb4dc;&#xc640; &#xbaa8;&#xc5ec;&#xc11c; &#xc815;&#xbcf4;&#xb97c; &#xc815;&#xb9ac;&#xd574;&#xbcf4;&#xae30;&#xb85c; &#xd558;&#xc600;&#xb294;&#xb370;,&#xa0;&apos;&#xd3d0;&#xc655;&#xc758; &#xd669;&#xae08;&apos;&#xc740;&#xa0;&#xc81c;&#xad6d;&#xad70;&#xc774; &#xc57d;&#xd0c8;&#xd588;&#xc744; &#xac00;&#xb2a5;&#xc131;&#xc740; &#xd76c;&#xbc15;&#xd558;&#xb2e4;&#xb294; &#xac83;&#xacfc; &#xc655;&#xad81; &#xc9c0;&#xd558;&#xc5d0; &#xc8c4;&#xc778;&#xc744; &#xc218;&#xc6a9;&#xd558;&#xb294; &#xac10;&#xc625;&#xc774; &#xc788;&#xc5c8;&#xb2e4;&#xace0;&#xb294; &#xd558;&#xb098; &#xad34;&#xbb3c; &#xc598;&#xae30;&#xb294; &#xc5c6;&#xc5c8;&#xb2e4;&#xb294; &#xac83;&#xc774;&#xc5c8;&#xb2e4;. &#xc54c;&#xd53c;&#xb178;&#xb294; &#xd3d0;&#xc655;&#xc758; &#xd669;&#xae08;&#xc774; &#xc788;&#xb294; &#xc7a5;&#xc18c;&#xb97c; &#xc54c; &#xac83; &#xac19;&#xc9c0;&#xb9cc;, &#xc544;&#xb80c;&#xbc1c;&#xb4dc;&#xc5d0;&#xac8c; &#xc774; &#xbaa8;&#xd5d8;&#xc758; &#xc9c4;&#xc9dc; &#xc774;&#xc720;&#xb97c; &#xbb3b;&#xac8c; &#xb41c;&#xb2e4;. &#xc774; &#xacfc;&#xc815;&#xc5d0;&#xc11c; &#xc544;&#xb80c;&#xbc1c;&#xb4dc;&#xb294; &#xc790;&#xc2e0;&#xc758; &#xcd9c;&#xc0dd;&#xacfc; &#xc131;&#xc7a5;&#xacfc;&#xc815;&#xc5d0; &#xb300;&#xd55c; &#xc774;&#xc57c;&#xae30;&#xb97c; &#xaebc;&#xb0b4;&#xba70; &apos;&#xc0ac;&#xb78c;&#xc740; &#xac00;&#xb09c; &#xb54c;&#xbb38;&#xc5d0; &#xbcc0;&#xd574;&#xbc84;&#xb9b0;&#xb2e4;&apos;&#xb294; &#xac78; &#xadf8; &#xb204;&#xad6c;&#xbcf4;&#xb2e4;&#xb3c4; &#xc798; &#xc54c;&#xace0; &#xc788;&#xc73c;&#xba70; &#xc790;&#xc2e0;&#xc740; &#xc54c;&#xb77c;&#xbbf8;&#xace0;&#xc758; &#xac00;&#xb09c;&#xd55c; &#xb3d9;&#xd3ec;&#xb97c; &#xc704;&#xd574; &#xbcf4;&#xbb3c;&#xc744; &#xc190;&#xc5d0; &#xb123;&#xace0; &#xc2f6;&#xb2e4;&#xace0; &#xc774;&#xc57c;&#xae30;&#xd55c;&#xb2e4;. &#xc774;&#xc5d0; &#xc54c;&#xd53c;&#xb178;&#xb294; &#xc544;&#xb80c;&#xbc1c;&#xb4dc;&#xc758; &#xc5f4;&#xc815;&#xc5d0; &#xbd80;&#xc751;&#xd558;&#xc790;&#xba70; &#xbc1c;&#xacac;&#xd55c; &#xbcf4;&#xbb3c;&#xc740; &#xae30;&#xbd80;&#xd558;&#xae30;&#xb85c; &#xd55c;&#xb2e4;.</p><p><br></p><p>&#xc54c;&#xd53c;&#xb178;&#xb294; &#xc7a5;&#xc18c;&#xb97c; &#xbc14;&#xafd4; &#xb85c;&#xd750; &#xc140; &#xd638;&#xc218;&#xb85c; &#xc774;&#xb3d9;&#xd558;&#xba70; &#xc81c;5 &#xc131;&#xb825;&#xc5d0; &#xc874;&#xc7ac;&#xd588;&#xb358; &apos;&#xc2a4;&#xce7c;&#xb77c;&apos;&#xb77c;&#xb294; &#xb3c4;&#xc2dc;&#xb97c; &#xc774;&#xc57c;&#xae30;&#xd558;&#xba70; &#xad34;&#xbb3c;&#xb85c; &#xbcc0;&#xd55c; &#xc655;&#xc871;&#xb4e4;&#xc744; &#xb5a8;&#xc5b4;&#xb728;&#xb838;&#xb2e4;&#xb294; &#xc655;&#xad81;&#xc758; &#xc9c0;&#xd558;&#xb780; &#xac10;&#xc625;&#xc774; &#xc544;&#xb2c8;&#xb77c; &#xb545;&#xc18d; &#xae4a;&#xc740; &#xacf3;&#xc5d0; &#xc788;&#xc744; &#xac83;&#xc73c;&#xb85c; &#xcd94;&#xce21;&#xb418;&#xb294; &#xc2a4;&#xce7c;&#xb77c;&#xc758; &#xc61b;&#xd130;&#xc77c; &#xac83;&#xc774;&#xb77c;&#xb294; &#xac00;&#xc124;&#xc744; &#xc138;&#xc6b4;&#xb2e4;. &#xad34;&#xbb3c;&#xc744; &#xc77c;&#xbd80;&#xb7ec; &#xc0b0; &#xcc44;&#xb85c; &#xb5a8;&#xc5b4;&#xb728;&#xb9b0; &#xc774;&#xc720;&#xb294; &#xc9c0;&#xd558; &#xc720;&#xc801;&#xc744; &#xc704;&#xd5d8;&#xd55c; &#xc7a5;&#xc18c;&#xb85c; &#xb9cc;&#xb4e4; &#xd544;&#xc694;&#xac00; &#xc788;&#xc5b4;&#xc11c;&#xc600;&#xace0;, &#xadf8;&#xc5d0; &#xb354;&#xd574; &#xd3d0;&#xc655;&#xc758; &#xd669;&#xae08;&#xc744; &#xc9c0;&#xd0a4;&#xb294; &#xd30c;&#xc218;&#xafbc;&#xc73c;&#xb85c; &#xc0bc;&#xae30; &#xc704;&#xd574;&#xc11c;, &#xadf8;&#xb9ac;&#xace0; &#xad81;&#xc911; &#xc8fc;&#xc220;&#xc0ac;&#xac00; &#xc5bd;&#xd600;&#xc788;&#xb2e4;&#xba74; &#xc9c0;&#xd558; &#xc720;&#xc801;&#xc73c;&#xb85c; &#xd1b5;&#xd558;&#xb294; &#xc785;&#xad6c;&#xb97c; &#xb9c8;&#xbc95;&#xc73c;&#xb85c; &#xc228;&#xaca8;&#xb480;&#xc744; &#xac00;&#xb2a5;&#xc131;&#xc774; &#xb192;&#xb2e4;&#xb294; &#xac83;. &#xc774;&#xc5d0; &#xc544;&#xb80c;&#xbc1c;&#xb4dc;&#xc640; &#xc54c;&#xd53c;&#xb178;&#xb294; &#xc721;&#xb85c;&#xb97c; &#xd1b5;&#xd574;, &#xbe5b;&#xc758; &#xc804;&#xc0ac;&#xb294; &#xd638;&#xc218; &#xae4a;&#xc740; &#xacf3;&#xc73c;&#xb85c; &#xc7a0;&#xc218;&#xd558;&#xc5ec; &#xc9c0;&#xd558; &#xc720;&#xc801;&#xc73c;&#xb85c; &#xb4e4;&#xc5b4;&#xac00;&#xb294; &#xc785;&#xad6c;&#xb97c; &#xcc3e;&#xc544;&#xbcf4;&#xae30;&#xb85c; &#xd55c;&#xb2e4;. &#xc544;&#xb2c8;&#xb098; &#xb2e4;&#xb97c;&#xae4c; &#xc720;&#xc801;&#xc73c;&#xb85c; &#xd1b5;&#xd558;&#xb294; &#xc785;&#xad6c;&#xb97c; &#xbc1c;&#xacac;&#xd588;&#xace0;, &#xbe5b;&#xc758; &#xc804;&#xc0ac;&#xc640; &#xc54c;&#xd53c;&#xb178;, &#xc544;&#xb80c;&#xbc1c;&#xb4dc;&#xb294; &#xc2a4;&#xce7c;&#xb77c; &#xc720;&#xc801;&#xc73c;&#xb85c; &apos;&#xd3d0;&#xc655;&#xc758; &#xd669;&#xae08;&apos;&#xc744; &#xcc3e;&#xc73c;&#xb7ec; &#xd5a5;&#xd558;&#xae30;&#xb85c; &#xd55c;&#xb2e4;.</p><p><br></p><p><br></p><p>&#xb358;&#xc804; &#xc804;&#xc6a9; BGM&#xc740; Far From Home(&#xace0;&#xd5a5;&#xc5d0;&#xc11c; &#xba40;&#xc5b4;&#xc9c0;&#xace0;)</p><p><br></p><h2>2. &#xacf5;&#xb7b5;</h2><h3>&#xc81c;1 &#xad6c;&#xac04;(&#xb85c;&#xd750; &#xc140; &#xc11d;&#xd68c;&#xb3d9;&#xad74;)</h3><p>&#xccab; &#xbc88;&#xc9f8; &#xc878;&#xac1c; &#xad6c;&#xac04;. &#xc8fc;&#xb85c; &#xb0ad;&#xce74;&#xb4e4;&#xc774; &#xb9ce;&#xc774; &#xb4f1;&#xc7a5;&#xd558;&#xb294;&#xb370;, &#xd30c;&#xd2f0;&#xc758; &#xc5ed;&#xb7c9;&#xc5d0; &#xb530;&#xb77c; &#xc801;&#xc808;&#xd788; &#xbaa8;&#xc740; &#xb4a4; &#xcc98;&#xb9ac;&#xd558;&#xb3c4;&#xb85d; &#xd55c;&#xb2e4;.</p><p><br></p><h3>&#xc81c;1 &#xbcf4;&#xc2a4; : &#xcf08;&#xd53c;(Kelpie)</h3><p>&#xcf08;&#xd53c;&#xc758; &#xc601;&#xc5ed;&#xc5d0; &#xb3c4;&#xb2ec;&#xd558;&#xba74; &#xb9d0;&#xc758; &#xbaa8;&#xc2b5;&#xc744; &#xd55c; &#xb9c8;&#xc218; &apos;&#xcf08;&#xd53c;&apos;&#xac00; &#xc788;&#xb2e4;.</p><p><br></p><p><strong>0. &#xc704;&#xd5d8; &#xc9c0;&#xb300;(Danger Zone) :</strong>&#xa0;&#xc804;&#xd22c;&#xac00; &#xc2dc;&#xc791;&#xb418;&#xba74; &#xd544;&#xb4dc; &#xc678;&#xacfd;&#xc5d0;&#xa0; &#xbb3c;&#xb3c5;&#xacfc; &#xbb3c;&#xc18d;&#xc131; &#xc800;&#xd56d; &#xac10;&#xc18c; &#xb514;&#xbc84;&#xd504;&#xb97c; &#xbd80;&#xc5ec;&#xd558;&#xb294; &#xc704;&#xd5d8; &#xc9c0;&#xb300;&#xac00; &#xc0dd;&#xae34;&#xb2e4;.</p><p><strong>1. &#xb4b7;&#xbc1c;&#xc9c8;(Torpedo) :</strong>&#xa0;&#xd0f1;&#xd06c;&#xbc84;&#xc2a4;&#xd130; &#xacf5;&#xaca9;. &#xc0dd;&#xc874;&#xae30;&#xc640; &#xd790;&#xc5c5; &#xc720;&#xc758;.</p><p><strong>2. &#xc19f;&#xad6c;&#xce58;&#xb294; &#xbc14;&#xb2e4;(Rising Seas) :</strong>&#xa0;&#xad11;&#xc5ed; &#xacf5;&#xaca9;&#xae30;. &#xd790;&#xb7ec;&#xb294; &#xd30c;&#xd2f0;&#xc6d0;&#xc758; HP &#xd68c;&#xbcf5;&#xc5d0; &#xc720;&#xc758;&#xd55c;&#xb2e4;.</p><p><strong>3. &#xc218;&#xb825; &#xbc00;&#xce58;&#xae30;(Hydro Push) :</strong>&#xa0;&#xcf08;&#xd53c;&#xac00; &#xd544;&#xb4dc;&#xc758; 4&#xacf3; &#xc911; &#xd55c; &#xacf3;&#xc73c;&#xb85c; &#xb3c4;&#xc57d;&#xd55c; &#xd6c4; &#xd30c;&#xb3c4;&#xb97c; &#xc77c;&#xc73c;&#xcf1c; &#xd30c;&#xd2f0;&#xc6d0;&#xb4e4;&#xc744; &#xb109;&#xbc31;&#xc2dc;&#xd0a8;&#xb2e4;. &#xc774; &#xb54c; &#xb109;&#xbc31; &#xbb34;&#xd6a8;&#xd654; &#xae30;&#xc220; &#xc0ac;&#xc6a9;&#xc774; &#xac00;&#xb2a5;&#xd558;&#xbbc0;&#xb85c; &#xac00;&#xb2a5;&#xd558;&#xba74; &#xc0ac;&#xc6a9;&#xd558;&#xb3c4;&#xb85d; &#xd55c;&#xb2e4;.</p><p><strong>4. &#xd53c; &#xc6c5;&#xb369;&#xc774;(Bloody Puddle) :</strong> &#xb79c;&#xb364; &#xb300;&#xc0c1; 2~3&#xba85;&#xc5d0;&#xac8c; &#xc6d0;&#xd615; &#xbc94;&#xc704; AoE &#xac1c;&#xc778; &#xb9c8;&#xd0b9;&#xc744; &#xbd80;&#xc5ec;&#xd558;&#xc5ec; &#xb300;&#xc0c1;&#xc774; &#xc11c; &#xc788;&#xb294; &#xc790;&#xb9ac;&#xb97c; &#xacf5;&#xaca9;&#xd55c;&#xb2e4;. &#xd53c;&#xaca9; &#xd6c4; &#xadf8; &#xc790;&#xb9ac;&#xc5d0; &#xc6c5;&#xb369;&#xc774;&#xc640; &#xc218;&#xb825; &#xad6c;&#xccb4;&#xac00; &#xd615;&#xc131;&#xb418;&#xc5b4; &#xd53c;&#xaca9;&#xb41c; &#xb300;&#xc0c1;&#xc744; &#xb530;&#xb77c;&#xb2e4;&#xb2cc;&#xb2e4;. &#xc6c5;&#xb369;&#xc774;&#xb97c; &#xbc1f;&#xc744; &#xc2dc; &#xbb3c;&#xb3c5; &#xb514;&#xbc84;&#xd504;&#xb97c; &#xbc1b;&#xc744; &#xc218; &#xc788;&#xc73c;&#xbbc0;&#xb85c; &#xc8fc;&#xc758;.</p><p><strong>4.1. &#xc218;&#xb825; &#xad6c;&#xccb4;(Hydrosphere) :</strong> &#xd53c; &#xc6c5;&#xb369;&#xc774;&#xc5d0; &#xd53c;&#xaca9;&#xb41c; &#xb300;&#xc0c1;&#xacfc; &#xc5f0;&#xacb0;&#xb418;&#xc5b4; &#xb530;&#xb77c;&#xb2e4;&#xb2c8;&#xb2e4;&#xac00; &#xc6d0;&#xd615; AoE &#xbc94;&#xc704; &#xacf5;&#xaca9;&#xc744; &#xd55c;&#xb2e4;. &#xc774; &#xb54c; &#xd53c;&#xaca9;&#xb418;&#xba74; &#xbb3c;&#xc18d;&#xc131; &#xc800;&#xd56d; &#xac10;&#xc18c; &#xb514;&#xbc84;&#xd504;&#xb97c; &#xb9de;&#xac8c; &#xb418;&#xbbc0;&#xb85c; &#xc8fc;&#xc758;.</p><p><strong>5. &#xc218;&#xb825; &#xb2f9;&#xae30;&#xae30;(Hydro Pull) :</strong> &#xcf08;&#xd53c;&#xac00; &#xd544;&#xb4dc;&#xc758; 4&#xacf3; &#xc911; &#xd55c; &#xacf3;&#xc73c;&#xb85c; &#xb2e4;&#xc2dc; &#xb3c4;&#xc57d;&#xd558;&#xc5ec; &#xc790;&#xc2e0;&#xc774; &#xc788;&#xb294; &#xbc29;&#xd5a5;&#xc73c;&#xb85c; &#xb04c;&#xc5b4;&#xb2f9;&#xae34;&#xb2e4;.</p><p><br></p><p>&#xc774;&#xd6c4; &#xae30;&#xbbf9; &#xd328;&#xd134;&#xc774; &#xadf8;&#xb300;&#xb85c; &#xbc18;&#xbcf5; &#xb418;&#xbbc0;&#xb85c; &#xd328;&#xd134;&#xc744; &#xd30c;&#xd6fc;&#xd558;&#xc5ec; &#xcc98;&#xb9ac;&#xd558;&#xace0; &#xb2e4;&#xc74c; &#xad6c;&#xac04;&#xc73c;&#xb85c; &#xb118;&#xc5b4;&#xac00;&#xb3c4;&#xb85d; &#xd55c;&#xb2e4;.</p><p><br></p><h3>&#xc81c;2 &#xad6c;&#xac04;(&#xc131;&#xb2f9; &#xad6c;&#xc5ed;)</h3><p>&#xb450; &#xbc88;&#xc9f8; &#xc878;&#xac1c; &#xad6c;&#xac04;. &#xc774;&#xbc88;&#xc5d0;&#xb294; &#xc554;&#xc11d; &#xd3ec;&#xbc30;&#xb4dc;&#xc640; &#xb2e4;&#xb77c; &#xd30c;&#xc218;&#xafbc;, &#xc694;&#xacb0;&#xc11d; &#xd30c;&#xc218;&#xafbc; &#xc878;&#xac1c;&#xac00; &#xb300;&#xac70; &#xb4f1;&#xc7a5;&#xd55c;&#xb2e4;. &#xc5ed;&#xc2dc; &#xd30c;&#xd2f0;&#xc758; &#xc5ed;&#xb7c9;&#xc5d0; &#xb530;&#xb77c;&#xc11c; &#xc801;&#xb2f9;&#xd788; &#xbaa8;&#xc544;&#xc11c; &#xcc98;&#xb9ac;&#xd558;&#xb294; &#xac83;&#xc744; &#xad8c;&#xc7a5;&#xd55c;&#xb2e4;.</p><p><br></p><p id=\"posHere\"><br></p><h3>&#xc81c;2 &#xbcf4;&#xc2a4; : &#xc61b; &#xc874;&#xc7ac;(The Old One)</h3><p>&#xbd09;&#xc778;&#xb41c; &#xbb38; &#xd544;&#xb4dc;&#xc5d0; &#xb3c4;&#xcc29;&#xd558;&#xba74; &#xadf8; &#xc55e;&#xc5d0;&#xb294; &#xae30;&#xad34;&#xd55c; &#xd1a0;&#xd15c; &#xd615;&#xd0dc;&#xc758; &apos;&#xc61b; &#xc874;&#xc7ac;&apos;&#xac00; &#xb450; &#xbc88;&#xc9f8; &#xc9c0;&#xc810;&#xc758; &#xbcf4;&#xc2a4;&#xb85c; &#xb4f1;&#xc7a5;&#xd55c;&#xb2e4;.</p><p><br></p><p><strong>1. &#xb9c8;&#xad11;&#xc120;(Mystic Light) :</strong>&#xa0;45&#xb3c4; &#xbc94;&#xc704;&#xc758; &#xbd80;&#xcc44;&#xaf34; &#xbc94;&#xc704; &#xacf5;&#xaca9;. &#xbc94;&#xc704; &#xc7a5;&#xd310;&#xc774; &#xb4f1;&#xc7a5;&#xd558;&#xbbc0;&#xb85c; &#xac00;&#xbccd;&#xac8c; &#xd53c;&#xd558;&#xb3c4;&#xb85d; &#xd55c;&#xb2e4;.</p><p><strong>2. &#xb9c8;&#xad11;&#xc5fc;(Mystic Flame) :</strong>&#xa0;&#xb79c;&#xb364; &#xb300;&#xc0c1; &#xc6d0;&#xd615; AoE &#xc7a5;&#xd310; &#xacf5;&#xaca9;. &#xbc94;&#xc704;&#xac00; &#xc740;&#xadfc; &#xd06c;&#xae30; &#xb54c;&#xbb38;&#xc5d0; &#xc7a5;&#xd310; &#xbc94;&#xc704;&#xac00; &#xbcf4;&#xc774;&#xba74; &#xd53c;&#xd574;&#xc900;&#xb2e4;.</p><p><br></p><blockquote><p><strong>[&#xc61b; &#xc874;&#xc7ac;]</strong></p><p><strong>&#x2169;&#x2169;&#x25b3;&#x3131;&#x3163;&#x3145;&#x315c;&#x3139;&#x25b3;&#x2169;&#x2169;&#x25ce;&#x3141;&#x314f;&#x3139;&#x3155;&#x3131;&#x25ce;&#x2169;&#x2169;&#x25bc;&#x3131;&#x3157;&#x3147;&#x3131;&#x3161;&#x3142;&#x25bc;&#x2169;&#x2169;&#x3148;&#x314f;&#x314d;&#x3157;&#x3131;,&#xa0;&#x3148;&#x314f;&#x314d;&#x3157;&#x3131;,&#xa0;&#x3148;&#x314f;&#x314d;&#x3157;&#x3131;,&#xa0;&#x3148;&#x314f;&#x314d;&#x3157;&#x3131;.......</strong></p></blockquote><p>&#xc61b; &#xc874;&#xc7ac;&#xac00; &#xc911;&#xc559;&#xc73c;&#xb85c; &#xc774;&#xb3d9;&#xd558;&#xc5ec; 4&#xac1c;&#xc758; &#xc61b; &#xc874;&#xc7ac;&#xc758; &#xd658;&#xc601;&#xc744; &#xc18c;&#xd658;&#xd558;&#xba70; &#xc790;&#xc2e0;&#xc740; &#xbb34;&#xc801; &#xc0c1;&#xd0dc;&#xac00; &#xb41c;&#xb2e4;. &#xadf8;&#xc640; &#xb3d9;&#xc2dc;&#xc5d0; &#xd658;&#xc601;&#xc744; &#xc790;&#xc2e0;&#xacfc; &#xc5f0;&#xacb0;&#xd558;&#xc5ec; &#xc790;&#xd3ed; &#xba85;&#xb839;&#xc744; &#xb0b4;&#xb9b0;&#xb2e4;.</p><p><br></p><p><strong>3. &#xc790;&#xd3ed; &#xba85;&#xb839;(Order to Self-destruct) :</strong>&#xa0;&#xc61b; &#xc874;&#xc7ac;&#xc758; &#xd658;&#xc601;&#xc744; &#xc18c;&#xd658;&#xd55c; &#xd6c4; &#xc790;&#xc2e0;&#xc740; &#xbb34;&#xc801;&#xc0c1;&#xd0dc;&#xac00; &#xb41c; &#xb4a4; &#xc790;&#xd3ed; &#xba85;&#xb839;&#xc744; &#xb0b4;&#xb9b0;&#xb2e4;. &#xc61b; &#xc874;&#xc7ac;&#xc758; &#xd658;&#xc601;&#xc744; &#xc790;&#xd3ed; &#xba85;&#xb839;&#xc774; &#xc2dc;&#xc804;&#xc774; &#xc644;&#xb8cc;&#xd558;&#xae30; &#xc804;&#xae4c;&#xc9c0; &#xd574;&#xce58;&#xc6b0;&#xba74; &#xb41c;&#xb2e4;.</p><p><strong>3.1. &#xc61b; &#xc874;&#xc7ac;&#xc758; &#xd658;&#xc601; (Subservient) :</strong>&#xa0;&#xc61b; &#xc874;&#xc7ac;&#xac00; &#xc18c;&#xd658;&#xd55c; &#xc878;&#xac1c;. &#xc2dc;&#xacc4; &#xbc29;&#xd5a5; &#xd639;&#xc740; &#xc2dc;&#xacc4; &#xbc18;&#xb300;&#xbc29;&#xd5a5;&#xc73c;&#xb85c; &#xd544;&#xb4dc;&#xb97c; &#xb3cc;&#xace0; &#xb3c8;&#xb2e4;. &#xcc98;&#xc74c;&#xacfc; &#xb450; &#xbc88;&#xc9f8;&#xc5d0;&#xb294; 4&#xac1c;&#xac00; &#xb4f1;&#xc7a5;&#xd558;&#xace0;&#xa0;&#xc774;&#xd6c4; &#xc18c;&#xd658; &#xc2dc;&#xc5d0;&#xb294; 8&#xac1c;&#xac00; &#xb4f1;&#xc7a5;&#xd55c;&#xb2e4;.</p><p><br></p><blockquote><p><strong>[&#xc61b; &#xc874;&#xc7ac;]</strong></p><p><strong>&#x2169;&#x2169;&#x25b3;&#x3131;&#x3163;&#x3145;&#x315c;&#x3139;&#x25b3;&#x2169;&#x2169;&#x25ce;&#x3145;&#x314f;&#x3145;&#x315c;&#x3139;&#x25ce;&#x2169;&#x2169;&#x25bc;&#x3142;&#x3155;&#x3134;&#x3147;&#x3163;&#x25bc;&#x2169;&#x2169; &#x3148;&#x3153;&#x3148;&#x315c;,&#xa0;&#x3148;&#x3153;&#x3148;&#x315c;,&#xa0;&#x3148;&#x3153;&#x3148;&#x315c;,&#xa0;&#x3148;&#x3153;&#x3148;&#x315c;......</strong></p></blockquote><p>&#xc774;&#xbc88;&#xc5d0;&#xb294; &#xc61b; &#xc874;&#xc7ac;&#xac00; &#xc911;&#xc559;&#xc73c;&#xb85c; &#xc774;&#xb3d9;&#xd55c; &#xb4a4;, &#xd30c;&#xd2f0;&#xc6d0; &#xc804;&#xc6d0;&#xc744; &#xbcc0;&#xd654;&#xc2dc;&#xd0a8;&#xb2e4;.</p><p><br></p><p><strong>4. &#xbcc0;&#xd654;&#xad11;(Shifting Light) :</strong>&#xa0;&#xc2dc;&#xc804;&#xc774; &#xc885;&#xb8cc;&#xb418;&#xba74; &#xd30c;&#xd2f0;&#xc6d0; &#xc804;&#xc6d0;&#xc744; &#xc2a4;&#xd504;&#xb9ac;&#xac74;&#xc73c;&#xb85c; &#xbcc0;&#xc2e0;&#xc2dc;&#xd0a8;&#xb2e4;.</p><p><br></p><blockquote><p><strong>[&#xc61b; &#xc874;&#xc7ac;]</strong></p><p><strong>&#x2169;&#x2169;&#x25b3;&#x3131;&#x3163;&#x3145;&#x315c;&#x3139;&#x25b3;&#x2169;&#x2169;&#x25ce;&#x3141;&#x314f;&#x3139;&#x3155;&#x3131;&#x25ce;&#x2169;&#x2169;&#x25bc;&#x3131;&#x3157;&#x3147;&#x3131;&#x3161;&#x3142;&#x25bc;&#x2169;&#x2169;&#x3148;&#x314f;&#x314d;&#x3157;&#x3131;,&#xa0;&#x3148;&#x314f;&#x314d;&#x3157;&#x3131;,&#xa0;&#x3148;&#x314f;&#x314d;&#x3157;&#x3131;,&#xa0;&#x3148;&#x314f;&#x314d;&#x3157;&#x3131;.......</strong></p></blockquote><p>&#xc774;&#xbc88;&#xc5d0;&#xb3c4; &#xc61b; &#xc874;&#xc7ac;&#xac00; &#xc790;&#xd3ed; &#xba85;&#xb839;&#xc744; &#xb0b4;&#xb9ac;&#xba74;&#xc11c; &#xc61b; &#xc874;&#xc7ac;&#xc758; &#xd658;&#xc601;&#xc744; 4&#xac1c;&#xb97c; &#xc18c;&#xd658;&#xd558;&#xb294;&#xb370;, &#xc774;&#xbc88;&#xc5d0;&#xb294; &#xc2a4;&#xd504;&#xb9ac;&#xac74;&#xc73c;&#xb85c; &#xbcc0;&#xc2e0;&#xd55c; &#xc0c1;&#xd0dc;&#xc774;&#xae30; &#xb54c;&#xbb38;&#xc5d0; &#xd2b9;&#xc218; &#xae30;&#xc220;&#xb85c; &#xc61b; &#xc874;&#xc7ac;&#xc758; &#xd658;&#xc601;&#xc744; &#xc5c6;&#xc560;&#xc57c; &#xd55c;&#xb2e4;.</p><p><br></p><p><strong>5. &#xc791;&#xb82c;&#xc554;(Shatterstone) :</strong>&#xa0;&#xc2a4;&#xd504;&#xb9ac;&#xac74;&#xc73c;&#xb85c; &#xbcc0;&#xc2e0;&#xd55c; &#xc0c1;&#xd0dc;&#xc5d0;&#xc11c; &#xc61b; &#xc874;&#xc7ac;&#xac00; &#xc9c0;&#xb098;&#xac00;&#xb294; &#xacbd;&#xb85c;&#xc5d0; &#xd3ed;&#xd0c4;&#xc744; &#xc124;&#xce58;&#xd55c;&#xb2e4;. &#xc61b; &#xc874;&#xc7ac;&#xc758; &#xd658;&#xc601;&#xc774; &#xc790;&#xb3d9;&#xc73c;&#xb85c; &#xc9c0;&#xb098;&#xac00;&#xba74;&#xc11c; 3&#xb9cc; &#xb370;&#xbbf8;&#xc9c0;&#xb85c; &#xd3ed;&#xd30c;&#xb41c;&#xb2e4;. 4&#xac1c;&#xb97c; &#xbaa8;&#xb450; &#xc5c6;&#xc560;&#xba74; &#xbcc0;&#xc2e0;&#xc774; &#xd574;&#xc81c;&#xb41c;&#xb2e4;.</p><p><br></p><p>&#xc774;&#xd6c4; &#xae30;&#xbbf9; &#xd328;&#xd134;&#xc774; &#xbc18;&#xbcf5;&#xb418;&#xb2e4;&#xac00; &#xc61b; &#xc874;&#xc7ac;&#xc758; HP&#xac00; 15% &#xc804;&#xd6c4;&#xac00; &#xb418;&#xba74; &#xb2e4;&#xc2dc; &#xbcc0;&#xd654;&#xad11;&#xc73c;&#xb85c; &#xc2a4;&#xd504;&#xb9ac;&#xac74;&#xc73c;&#xb85c; &#xbcc0;&#xc2e0;&#xc2dc;&#xd0a8; &#xb4a4;, &#xc774;&#xbc88;&#xc5d0;&#xb294; &#xd658;&#xc601; 8&#xac1c;&#xb97c; &#xbd88;&#xb7ec;&#xb0b8;&#xb2e4;. &#xc774;&#xc804;&#xacfc; &#xb611;&#xac19;&#xc774; &#xc791;&#xb82c;&#xc554;&#xc73c;&#xb85c; &#xacbd;&#xb85c;&#xc5d0; &#xd3ed;&#xd0c4;&#xc744; &#xc124;&#xce58;&#xd558;&#xc5ec; &#xc5c6;&#xc560;&#xace0; &#xbcc0;&#xc2e0;&#xc744; &#xd574;&#xc81c;&#xd574;&#xc8fc;&#xba74; &#xb41c;&#xb2e4;. &#xb0a8;&#xc740; HP&#xb97c; &#xae4e;&#xc544;&#xb0b4;&#xc5b4; &#xcc98;&#xb9ac;&#xd574;&#xc900; &#xb4a4; &#xb2e4;&#xc74c; &#xad6c;&#xac04;&#xc73c;&#xb85c; &#xb118;&#xc5b4;&#xac00;&#xba74; &#xb41c;&#xb2e4;.</p><p><br></p><h3>&#xc81c;3 &#xad6c;&#xac04;(&#xc720;&#xd3d0; &#xad6c;&#xc5ed;)</h3><p>&#xc138; &#xbc88;&#xc9f8; &#xc878;&#xac1c; &#xad6c;&#xac04;. &#xc5ec;&#xae30;&#xc11c;&#xbd80;&#xd130;&#xb294; &#xbe5b;&#xb098;&#xc9c0; &#xc54a;&#xb294; &#xd638;&#xbb38;&#xcfe8;&#xb8e8;&#xc2a4;&#xc640; &#xc7a5;&#xbca0;&#xd1a0;&#xac00; &#xc774;&#xb3d9; &#xad6c;&#xac04;&#xc5d0;&#xc11c; &#xb4f1;&#xc7a5;&#xd558;&#xb294;&#xb370;, &#xc774;&#xb4e4;&#xc744; &#xcc98;&#xb9ac;&#xd558;&#xb2e4;&#xbcf4;&#xba74; &#xc7a5;&#xbca0;&#xd1a0;&#xac00; &#xc0ac;&#xb78c;&#xc758; &#xbaa8;&#xc2b5;&#xc73c;&#xb85c; &#xbcc0;&#xd55c;&#xb2e4;. &#xac01; &#xad6c;&#xac04;&#xc758; &#xc878;&#xac1c;&#xb4e4;&#xc744; &#xcc98;&#xce58;&#xd558;&#xba74; &#xc7a0;&#xc2dc; &#xc7a5;&#xbca0;&#xd1a0;&#xb85c; &#xbcc0;&#xc2e0;&#xd558;&#xb294;&#xb370;, &#xc804;&#xbc29;&#xc5d0; &#xae38;&#xc774; &#xb04a;&#xc5b4;&#xc838; &#xc788;&#xae30; &#xb54c;&#xbb38;&#xc5d0; &#xb9c8;&#xbc95;&#xc9c4;&#xc744; &#xbc1f;&#xace0; &#xc774;&#xb3d9;&#xd558;&#xb294; &#xac83;&#xc774; &#xc88b;&#xb2e4;. &#xb04a;&#xc5b4;&#xc9c4; &#xad6c;&#xac04;&#xc5d0;&#xc11c; &#xc911;&#xac04;&#xc5d0; &#xbcc0;&#xc2e0;&#xc744; &#xd574;&#xc81c;&#xd558;&#xb294; &#xc77c;&#xc740; &#xc5c6;&#xb3c4;&#xb85d; &#xd558;&#xc790;(&#xc9c4;&#xc9dc;&#xb85c; &#xb099;&#xc0ac;&#xd560; &#xc218; &#xc788;&#xb2e4;). &#xb9c8;&#xc9c0;&#xb9c9; &#xad6c;&#xac04;&#xae4c;&#xc9c0; &#xac00;&#xac8c; &#xb418;&#xba74; &#xc800;&#xc8fc;&#xbc1b;&#xc740; &#xd1a0;&#xc6b0;&#xc640; &#xadf8;&#xb9bc;&#xc790; &#xad34;&#xc218;&#xb85c; &#xbcc0;&#xc774;&#xd55c; &#xc655;&#xc871;&#xb4e4;&#xc774; &#xc788;&#xb2e4;. &#xc774;&#xb4e4;&#xc744; &#xbaa8;&#xb450; &#xcc98;&#xb9ac;&#xd574; &#xc8fc;&#xba74; &#xbcc0;&#xc774;&#xd55c; &#xc655;&#xc871;&#xc740; &#xb2e4;&#xc2dc; &#xbcf8;&#xb798;&#xc758; &#xc0ac;&#xb78c;&#xc758; &#xbaa8;&#xc2b5;&#xc73c;&#xb85c; &#xb3cc;&#xc544;&#xac04;&#xb2e4;.</p><p><br></p><h3>&#xcd5c;&#xc885; &#xbcf4;&#xc2a4; : &#xc785;&#xbc14;&#xb978; &#xd750;&#xb85c;&#xb4dc;&#xb9ad;(Hrodric Poisontongueone)</h3><p>&#xd14c;&#xc624;&#xb3c4;&#xb9ac;&#xd06c;&#xc758; &#xbcf4;&#xbb3c;&#xace0;&#xc5d0; &#xb3c4;&#xb2ec;&#xd558;&#xba74; &#xad34;&#xc218; &apos;&#xc785;&#xbc14;&#xb978; &#xd750;&#xb85c;&#xb4dc;&#xb9ad;&apos;&#xc774; &#xb4f1;&#xc7a5;&#xd55c;&#xb2e4;.&#xa0;</p><p><br></p><blockquote><p><strong>[&#xc785;&#xbc14;&#xb978; &#xd750;&#xb85c;&#xb4dc;&#xb9ad;]</strong></p><p><strong>&#xc6b0;&#xc624;&#xc624;&#xc624;&#xc624;&#xc624;&#xc624;! &#xc96c;&#xae34;&#xb2e4;, &#xc96c;&#xae34;&#xb2e4;, &#xbabd;&#xb545;, &#xc96c;&#xae34;&#xb2e4;&#xc544;&#xc544;&#xc544;!</strong></p></blockquote><p><strong>1. &#xb179;&#xc2a8; &#xbc1c;&#xd1b1;(Rusting Claw) :</strong>&#xa0;&#xd750;&#xb85c;&#xb4dc;&#xb9ad;&#xc774; &#xc55e;&#xbc1c;&#xc744; &#xb4e4;&#xc5b4; &#xc804;&#xbc29;&#xc744; &#xacf5;&#xaca9;. &#xcda9;&#xbd84;&#xd788; &#xd53c;&#xd560; &#xc2dc;&#xac04;&#xc744; &#xc81c;&#xacf5;&#xd558;&#xae30; &#xb54c;&#xbb38;&#xc5d0; &#xc660;&#xb9cc;&#xd558;&#xba74; &#xd53c;&#xd574;&#xc8fc;&#xb3c4;&#xb85d; &#xd55c;&#xb2e4;. &#xd53c;&#xaca9; &#xc2dc; &#xbc1b;&#xb294; &#xd53c;&#xd574; &#xc99d;&#xac00; &#xb514;&#xbc84;&#xd504;&#xb97c; &#xbc1b;&#xc73c;&#xbbc0;&#xb85c; &#xc8fc;&#xc758;.</p><p><strong>2. &#xaf2c;&#xb9ac; &#xc4f8;&#xae30;(Tail Drive) :</strong>&#xa0;&#xd750;&#xb85c;&#xb4dc;&#xb9ad;&#xc774; &#xaf2c;&#xb9ac;&#xb97c; &#xb4e4;&#xc5b4; &#xd6c4;&#xbc29;&#xc744; &#xacf5;&#xaca9;. &#xc5ed;&#xc2dc; &#xcda9;&#xbd84;&#xd788; &#xd53c;&#xd560; &#xc2dc;&#xac04;&#xc774; &#xc788;&#xc73c;&#xb2c8; &#xc804;&#xbc29;&#xc73c;&#xb85c; &#xd68c;&#xd53c;&#xd55c;&#xb2e4;. &#xd53c;&#xaca9; &#xc2dc; &#xbc1b;&#xb294; &#xd53c;&#xd574; &#xc99d;&#xac00; &#xb514;&#xbc84;&#xd504;&#xb97c; &#xbc1b;&#xc73c;&#xbbc0;&#xb85c; &#xc8fc;&#xc758;.</p><p><strong>3. &#xb300;&#xd68c;&#xc804;(The Spin) :</strong>&#xa0;&#xd750;&#xb85c;&#xb4dc;&#xb9ad; &#xc911;&#xc2ec;&#xc758; &#xac70;&#xb9ac; &#xac10;&#xc1e0; &#xacf5;&#xaca9;. &#xcd5c;&#xb300;&#xd55c; &#xba40;&#xb9ac; &#xb5a8;&#xc5b4;&#xc9c0;&#xb3c4;&#xb85d; &#xd55c;&#xb2e4;.</p><p><strong>4. &#xd63c;&#xb3c8;&#xc758; &#xace0;&#xb9ac; (Ring of Chaos) :</strong>&#xa0;&#xb79c;&#xb364; &#xb300;&#xc0c1;&#xc790;&#xc5d0;&#xac8c; &#xace0;&#xb9ac; &#xb9c8;&#xd0b9;&#xc744; &#xbd80;&#xc5ec;&#xd55c;&#xb2e4;. &#xb0b4;&#xbd80;&#xac00; &#xc548;&#xc804;&#xc9c0;&#xb300;&#xc774;&#xbbc0;&#xb85c; &#xb300;&#xc0c1;&#xc790; &#xcabd;&#xc73c;&#xb85c; &#xbaa8;&#xc5ec;&#xc11c; &#xd68c;&#xd53c;&#xd55c;&#xb2e4;.</p><p><br></p><blockquote><p><strong>[&#xc785;&#xbc14;&#xb978; &#xd750;&#xb85c;&#xb4dc;&#xb9ad;]</strong></p><p><strong>&#xc73c;&#xadf8;&#xadf8;&#xadf8;&#xadf8;&#xadf8;......! &#xc6a9;&#xc11c; &#xbabb; &#xc560;, &#xbabd;&#xb545;, &#xc96c;&#xaca8;&#xbc84;&#xb9ac;&#xac8c;&#xb530;&#xc544;&#xc544;!</strong></p></blockquote><p><strong>5. &#xacf5;&#xd3ec;&#xc758; &#xb208;&#xb3d9;&#xc790;(Eye of the Fire) :</strong>&#xa0;&#xb9c8;&#xc548; &#xacf5;&#xaca9;. &#xc2dc;&#xc120;&#xc744; &#xbc18;&#xb300;&#xb85c; &#xd558;&#xc5ec; &#xd68c;&#xd53c;&#xd558;&#xba74; &#xb41c;&#xb2e4;. &#xb9cc;&#xc57d; &#xd68c;&#xd53c;&#xac00; &#xb2a6;&#xc5c8;&#xc744; &#xacbd;&#xc6b0; &#xd63c;&#xb780; &#xb514;&#xbc84;&#xd504;&#xac00; &#xbd80;&#xc5ec;&#xb418;&#xba74;&#xc11c; &#xd30c;&#xd2f0;&#xc6d0;&#xc744; &#xb530;&#xb77c;&#xb2e4;&#xb2c8;&#xba70; &#xacf5;&#xaca9;&#xd558;&#xbbc0;&#xb85c; &#xc8fc;&#xc758;.</p><p><strong>6. &#xd63c;&#xb3c8;&#xc758; &#xc2ed;&#xc790;&#xac00;(Cross of Chaos) :</strong>&#xa0;&#xb79c;&#xb364; &#xb300;&#xc0c1;&#xc5d0;&#xac8c; &#xc2ed;&#xc790; &#xd615;&#xd0dc;&#xc758; AoE &#xbc94;&#xc704; &#xb9c8;&#xd0b9;&#xc744; &#xbd80;&#xc5ec;&#xd55c;&#xb2e4;.&#xa0;</p><p><strong>6.1. &#xd63c;&#xb3c8;&#xc758; &#xc6d0; (Circle of Chaos) :</strong>&#xa0;&#xb79c;&#xb364; &#xb300;&#xc0c1;&#xc5d0;&#xac8c; &#xc791;&#xc740; &#xc6d0;&#xd615; AoE &#xbc94;&#xc704; &#xb9c8;&#xd0b9;&#xc774; &#xd45c;&#xc2dc;&#xb41c;&#xb2e4;. &#xc77c;&#xc815; &#xc2dc;&#xac04;&#xc774; &#xacbd;&#xacfc;&#xb418;&#xba74; &#xb300;&#xc0c1;&#xc790;&#xc5d0;&#xac8c; &#xd53c;&#xaca9;&#xb41c;&#xb2e4;.</p><p><strong>7. &#xbe44;&#xd1b5;&#xd55c; &#xc678;&#xce68;(Words of Woe) :</strong>&#xa0;&#xb79c;&#xb364; &#xb300;&#xc0c1; 1&#xba85;&#xc529; 3&#xbc88;&#xc744; &#xbc14;&#xb77c;&#xbcf4;&#xba74;&#xc11c; &#xc804;&#xbc29;&#xc73c;&#xb85c; &#xbe54; &#xacf5;&#xaca9;&#xc744; &#xd55c;&#xb2e4;. &#xbc14;&#xb77c;&#xbcf4;&#xb294; &#xbc29;&#xd5a5;&#xc73c;&#xb85c; &#xc11c; &#xc788;&#xb2e4;&#xac00; &#xba87; &#xcd08; &#xb4a4;&#xc5d0; &#xacf5;&#xaca9;&#xc774; &#xb098;&#xc624;&#xae30; &#xb54c;&#xbb38;&#xc5d0; &#xc790;&#xc2e0;&#xc744; &#xbc14;&#xb77c;&#xbcf8;&#xb2e4; &#xc2f6;&#xb2e4;&#xba74; &#xbc14;&#xb85c; &#xd68c;&#xd53c;&#xd558;&#xb3c4;&#xb85d; &#xd55c;&#xb2e4;.</p><p><br></p><p>&#xae30;&#xbbf9; &#xd328;&#xd134;&#xc740; &#xadf8;&#xb300;&#xb85c; &#xbc18;&#xbcf5;&#xc774;&#xbbc0;&#xb85c; &#xc801;&#xc808;&#xd788; &#xd328;&#xd134;&#xc744; &#xd30c;&#xd6fc;&#xd558;&#xc5ec; &#xcc98;&#xb9ac;&#xd558;&#xc5ec; &#xd750;&#xb85c;&#xb4dc;&#xb9ad;&#xc758; HP&#xb97c; 0%&#xb85c; &#xb9cc;&#xb4e4;&#xba74; &#xc2b9;&#xb9ac;&#xd560; &#xc218; &#xc788;&#xb2e4;.</p><p><br></p><h2>3. &#xbcf4;&#xc0c1;</h2><p>&#xbcf4;&#xc0c1;&#xc740; &#xc54c;&#xb77c;&#xadf8; &#xc11d;&#xd310; : &#xd5c8;&#xad6c; 50&#xac1c;&#xc640; &#xcc3d;&#xc138; 20&#xac1c;, 315 &#xb808;&#xbca8;&#xc758; &quot;&#xc2a4;&#xce7c;&#xb77c;&quot; &#xc7a5;&#xbe44;&#xc640; &#xc7a5;&#xc2e0;&#xad6c; &#xc138;&#xd2b8;, &#xaf2c;&#xb9c8; &#xce5c;&#xad6c; &quot;&#xae68;&#xc54c;&#xbb3c;&#xbc94;&quot;&#xc744; &#xd68d;&#xb4dd;&#xd560; &#xc218; &#xc788;&#xb2e4;. <span style=\"text-decoration: line-through;\" data-mce-style=\"text-decoration: line-through;\">&#xaf2c;&#xb9c8;&#xce5c;&#xad6c;&#xac00; &#xad49;&#xc7a5;&#xd788; &#xadc0;&#xc5fd;&#xb2e4;...</span></p><p><br></p><h2>4. &#xc774;&#xd6c4;&#xc758; &#xc774;&#xc57c;&#xae30;(&#xc2a4;&#xd3ec;&#xc77c;&#xb7ec; &#xc8fc;&#xc758;)</h2><p>&#xc774; &#xc774;&#xc57c;&#xae30;&#xb294; &quot;&#xd64d;&#xb828;&#xc758; &#xd574;&#xbc29;&#xc790;&quot; &#xba54;&#xc778; &#xd018;&#xc2a4;&#xd2b8;&#xc778; &quot;&#xc601;&#xc6c5;&#xc758; &#xadc0;&#xd658;&quot;&#xc758; &#xd575;&#xc2ec; &#xb0b4;&#xc6a9;&#xc744; &#xb2f4;&#xace0; &#xc788;&#xc73c;&#xbbc0;&#xb85c; &#xc544;&#xc9c1; &#xc9c4;&#xd589;&#xc744; &#xc548;&#xd55c; &#xc0ac;&#xb78c;&#xc774;&#xb098; &#xc2a4;&#xd3ec;&#xc77c;&#xb7ec;&#xb97c; &#xc2eb;&#xc5b4;&#xd558;&#xb294; &#xbd84;&#xb4e4;&#xc740; &#xc5f4;&#xb78c;&#xd558;&#xc9c0; &#xc54a;&#xc744; &#xac83;&#xc744; &#xad8c;&#xc7a5;&#xd55c;&#xb2e4;.</p><p><br></p><p><br></p><p><br></p><p><br></p><p><br></p><p><br></p><div contenteditable=\"false\"><div class=\"alert alert-warning\" contenteditable=\"true\" style=\"text-align: center;\" data-mce-style=\"text-align: center;\">&#x203b;&#xc791;&#xc911; &#xc2a4;&#xd3ec;&#xc77c;&#xb7ec; &#xc8fc;&#xc758; : &#xc774; &#xd2c0; &#xc544;&#xb798;&#xb85c;&#xb294; &#xd574;&#xb2f9; &#xc791;&#xd488;&#xc758; &#xd575;&#xc2ec;&#xc801;&#xc778; &#xb0b4;&#xc6a9;&#xc774; &#xc788;&#xc2b5;&#xb2c8;&#xb2e4;.</div></div><p>&#xd750;&#xb85c;&#xb4dc;&#xb9ad;&#xc740; &#xad34;&#xc218;&#xc758; &#xbaa8;&#xc2b5;&#xc5d0;&#xc11c; &#xbcf8;&#xb798; &#xbaa8;&#xc2b5;&#xc73c;&#xb85c; &#xb3cc;&#xc544;&#xc624;&#xae30;&#xb294; &#xd558;&#xc600;&#xc73c;&#xb098; &#xbc14;&#xb85c; &#xc5d0;&#xd14c;&#xb974;&#xacc4;&#xb85c; &#xb3cc;&#xc544;&#xac00;&#xace0; &#xb9cc;&#xb2e4;. &#xc5b4;&#xcc0c;&#xb418;&#xc5c8;&#xb358; &#xd3d0;&#xc655;&#xc758; &#xd669;&#xae08;&#xc744; &#xbc1c;&#xacac;&#xd558;&#xac8c; &#xb41c; &#xc54c;&#xd53c;&#xb178; &#xc77c;&#xd589;&#xacfc; &#xbe5b;&#xc758; &#xc804;&#xc0ac;. &#xd14c;&#xc624;&#xb3c4;&#xb9ac;&#xd06c;&#xc758; &#xbcf4;&#xbb3c;&#xace0;&#xb97c; &#xbc1c;&#xacac;&#xd55c; &#xc138; &#xc0ac;&#xb78c;&#xc740; &#xc774;&#xbc88; &#xbaa8;&#xd5d8;&#xc740; &#xb300;&#xc131;&#xacf5;&#xc774;&#xc5c8;&#xb2e4;&#xba70; &#xae30;&#xbed0;&#xd55c;&#xb2e4;. &#xc544;&#xb80c;&#xbc1c;&#xb4dc;&#xb294; &#xbc1c;&#xacac;&#xd55c; &#xbcf4;&#xbb3c;&#xc744; &#xae30;&#xbd80;&#xd558;&#xae30; &#xc704;&#xd574; &#xb9ac;&#xc138;&#xb97c; &#xcc3e;&#xc73c;&#xb7ec; &#xac04;&#xb2e4;. &#xbe5b;&#xc758; &#xc804;&#xc0ac;&#xc640; &#xc544;&#xb80c;&#xbc1c;&#xb4dc;, &#xc54c;&#xd53c;&#xb178;&#xb294; &#xd3d0;&#xc655; &#xd14c;&#xc624;&#xb3c4;&#xb9ac;&#xd06c;&#xac00; &#xc228;&#xaca8;&#xb454; &#xbcf4;&#xbb3c;&#xc744; &#xbc1c;&#xacac;&#xd55c; &#xbaa8;&#xd5d8;&#xc5d0; &#xb300;&#xd574; &#xc774;&#xc57c;&#xae30;&#xd558;&#xba70; &#xc774; &#xbcf4;&#xbb3c;&#xc744; &#xac00;&#xb09c;&#xd55c; &#xc0ac;&#xb78c;&#xb4e4;&#xc744; &#xc704;&#xd574; &#xc368;&#xb2ec;&#xb77c;&#xace0; &#xbd80;&#xd0c1;&#xd55c;&#xb2e4;. &#xc54c;&#xd53c;&#xb178;&#xb3c4; &#xc655;&#xad81; &#xc9c0;&#xd558; &#xac10;&#xc625;&#xc5d0;&#xc11c; &#xbcf4;&#xbb3c;&#xc774; &#xc788;&#xb294; &#xacf3;&#xc73c;&#xb85c; &#xac00;&#xb294; &#xc9c0;&#xb3c4;&#xb3c4; &#xb9cc;&#xb4e4;&#xc5b4;&#xb480;&#xc73c;&#xba70; &#xb098;&#xc911;&#xc5d0; &#xd574;&#xbc29;&#xad70; &#xd22c;&#xc0ac;&#xb4e4; &#xc911; &#xc2e0;&#xb8b0;&#xd560; &#xb9cc;&#xd55c; &#xc774;&#xb97c; &#xc120;&#xbc1c;&#xd558;&#xc5ec; &#xd68c;&#xc218;&#xd558;&#xb7ec; &#xbcf4;&#xb0bc; &#xac83;&#xc744; &#xb2f9;&#xbd80;&#xd55c;&#xb2e4;.</p><p><br></p><p>&#xc5ec;&#xae30;&#xc5d0; &#xc544;&#xb80c;&#xbc1c;&#xb4dc;&#xb294; &#xd3d0;&#xc655;&#xc758; &#xd669;&#xae08;&#xc744; &#xc790;&#xbcf8;&#xc73c;&#xb85c; &#xc0bc;&#xc544; &#xc54c;&#xb77c;&#xbbf8;&#xace0;&#xb97c; &#xc9c0;&#xc6d0;&#xd558;&#xb294; &#xacc4;&#xd68d;&#xc744; &#xc54c;&#xd53c;&#xb178;&#xac00; &#xac80;&#xd1a0;&#xd574;&#xc904; &#xac83;&#xc744; &#xbd80;&#xd0c1;&#xd55c;&#xb2e4;. &#xb9ac;&#xc138;&#xb3c4; &#xc911;&#xb9bd;&#xc778; &apos;&#xc0c8;&#xbcbd;&apos; &#xc785;&#xc7a5;&#xc5d0;&#xc11c; &#xacc4;&#xd68d;&#xc548;&#xc744; &#xb9cc;&#xb4e4;&#xc5c8;&#xc73c;&#xba74; &#xc88b;&#xaca0;&#xb2e4;&#xace0; &#xd558;&#xb294;&#xb370;, &#xc54c;&#xd53c;&#xb178;&#xb294; &#xc774;&#xb97c; &#xc218;&#xb77d;&#xd55c;&#xb2e4;.</p><div data-mce-bogus=\"all\" class=\"mce-resize-bar mce-resize-bar-row\" unselectable=\"on\" data-mce-resize=\"false\" data-mce-style=\"cursor: row-resize; margin: 0; padding: 0; position: absolute; left: 15px; top: 164px; height: 4px; width: 590px; \" style=\"cursor: row-resize; margin: 0; padding: 0; position: absolute; left: 15px; top: 164px; height: 4px; width: 590px; \" data-row=\"0\"></div><div data-mce-bogus=\"all\" class=\"mce-resize-bar mce-resize-bar-row\" unselectable=\"on\" data-mce-resize=\"false\" data-mce-style=\"cursor: row-resize; margin: 0; padding: 0; position: absolute; left: 15px; top: 213px; height: 4px; width: 590px; \" style=\"cursor: row-resize; margin: 0; padding: 0; position: absolute; left: 15px; top: 213px; height: 4px; width: 590px; \" data-row=\"1\"></div><div data-mce-bogus=\"all\" class=\"mce-resize-bar mce-resize-bar-row\" unselectable=\"on\" data-mce-resize=\"false\" data-mce-style=\"cursor: row-resize; margin: 0; padding: 0; position: absolute; left: 15px; top: 264px; height: 4px; width: 590px; \" style=\"cursor: row-resize; margin: 0; padding: 0; position: absolute; left: 15px; top: 264px; height: 4px; width: 590px; \" data-row=\"2\"></div><div data-mce-bogus=\"all\" class=\"mce-resize-bar mce-resize-bar-row\" unselectable=\"on\" data-mce-resize=\"false\" data-mce-style=\"cursor: row-resize; margin: 0; padding: 0; position: absolute; left: 15px; top: 315px; height: 4px; width: 590px; \" style=\"cursor: row-resize; margin: 0; padding: 0; position: absolute; left: 15px; top: 315px; height: 4px; width: 590px; \" data-row=\"3\"></div><div data-mce-bogus=\"all\" class=\"mce-resize-bar mce-resize-bar-row\" unselectable=\"on\" data-mce-resize=\"false\" data-mce-style=\"cursor: row-resize; margin: 0; padding: 0; position: absolute; left: 15px; top: 366px; height: 4px; width: 590px; \" style=\"cursor: row-resize; margin: 0; padding: 0; position: absolute; left: 15px; top: 366px; height: 4px; width: 590px; \" data-row=\"4\"></div><div data-mce-bogus=\"all\" class=\"mce-resize-bar mce-resize-bar-row\" unselectable=\"on\" data-mce-resize=\"false\" data-mce-style=\"cursor: row-resize; margin: 0; padding: 0; position: absolute; left: 15px; top: 417px; height: 4px; width: 590px; \" style=\"cursor: row-resize; margin: 0; padding: 0; position: absolute; left: 15px; top: 417px; height: 4px; width: 590px; \" data-row=\"5\"></div><div data-mce-bogus=\"all\" class=\"mce-resize-bar mce-resize-bar-row\" unselectable=\"on\" data-mce-resize=\"false\" data-mce-style=\"cursor: row-resize; margin: 0; padding: 0; position: absolute; left: 15px; top: 468px; height: 4px; width: 590px; \" style=\"cursor: row-resize; margin: 0; padding: 0; position: absolute; left: 15px; top: 468px; height: 4px; width: 590px; \" data-row=\"6\"></div><div data-mce-bogus=\"all\" class=\"mce-resize-bar mce-resize-bar-row\" unselectable=\"on\" data-mce-resize=\"false\" data-mce-style=\"cursor: row-resize; margin: 0; padding: 0; position: absolute; left: 15px; top: 519px; height: 4px; width: 590px; \" style=\"cursor: row-resize; margin: 0; padding: 0; position: absolute; left: 15px; top: 519px; height: 4px; width: 590px; \" data-row=\"7\"></div><div data-mce-bogus=\"all\" class=\"mce-resize-bar mce-resize-bar-row\" unselectable=\"on\" data-mce-resize=\"false\" data-mce-style=\"cursor: row-resize; margin: 0; padding: 0; position: absolute; left: 15px; top: 570px; height: 4px; width: 590px; \" style=\"cursor: row-resize; margin: 0; padding: 0; position: absolute; left: 15px; top: 570px; height: 4px; width: 590px; \" data-row=\"8\"></div><div data-mce-bogus=\"all\" class=\"mce-resize-bar mce-resize-bar-col\" unselectable=\"on\" data-mce-resize=\"false\" data-mce-style=\"cursor: col-resize; margin: 0; padding: 0; position: absolute; left: 161px; top: 135px; height: 438px; width: 4px; \" style=\"cursor: col-resize; margin: 0; padding: 0; position: absolute; left: 161px; top: 135px; height: 438px; width: 4px; \" data-col=\"0\"></div><div data-mce-bogus=\"all\" class=\"mce-resize-bar mce-resize-bar-col\" unselectable=\"on\" data-mce-resize=\"false\" data-mce-style=\"cursor: col-resize; margin: 0; padding: 0; position: absolute; left: 308px; top: 135px; height: 438px; width: 4px; \" style=\"cursor: col-resize; margin: 0; padding: 0; position: absolute; left: 308px; top: 135px; height: 438px; width: 4px; \" data-col=\"1\"></div><div data-mce-bogus=\"all\" class=\"mce-resize-bar mce-resize-bar-col\" unselectable=\"on\" data-mce-resize=\"false\" data-mce-style=\"cursor: col-resize; margin: 0; padding: 0; position: absolute; left: 455px; top: 135px; height: 438px; width: 4px; \" style=\"cursor: col-resize; margin: 0; padding: 0; position: absolute; left: 455px; top: 135px; height: 438px; width: 4px; \" data-col=\"2\"></div><div data-mce-bogus=\"all\" class=\"mce-resize-bar mce-resize-bar-col\" unselectable=\"on\" data-mce-resize=\"false\" data-mce-style=\"cursor: col-resize; margin: 0; padding: 0; position: absolute; left: 602px; top: 135px; height: 438px; width: 4px; \" style=\"cursor: col-resize; margin: 0; padding: 0; position: absolute; left: 602px; top: 135px; height: 438px; width: 4px; \" data-col=\"3\"></div>\r\n\t\t\t</div>"
}