{
	"id": "plIAPx2CldZVYsj",
	"json": "{\"id\":\"plIAPx2CldZVYsj\",\"url\":\"http://ko.areumdri.wikidok.net/wp-d/58063630dfd5faeb5313f863/View\",\"loadedUrl\":\"http://ko.areumdri.wikidok.net/wp-d/58063630dfd5faeb5313f863/View\",\"uniqueKey\":\"http://ko.areumdri.wikidok.net/wp-d/58063630dfd5faeb5313f863/View\",\"method\":\"GET\",\"noRetry\":false,\"retryCount\":0,\"errorMessages\":[],\"headers\":{},\"userData\":{\"__crawlee\":{\"state\":4}},\"handledAt\":\"2022-12-31T14:14:45.533Z\"}",
	"method": "GET",
	"orderNo": null,
	"retryCount": 0,
	"uniqueKey": "http://ko.areumdri.wikidok.net/wp-d/58063630dfd5faeb5313f863/View",
	"url": "http://ko.areumdri.wikidok.net/wp-d/58063630dfd5faeb5313f863/View"
}